{
    "relationships": [
        {
            "relationshipName": "address",
            "otherEntityName": "address",
            "relationshipType": "one-to-one",
            "otherEntityField": "id",
            "ownerSide": true,
            "otherEntityRelationshipName": "profile"
        }
    ],
    "fields": [
        {
            "fieldName": "creationTime",
            "fieldType": "ZonedDateTime",
            "fieldValidateRules": [
                "required"
            ]
        },
        {
            "fieldName": "modificationTime",
            "fieldType": "ZonedDateTime"
        },
        {
            "fieldName": "firmName",
            "fieldType": "String",
            "fieldValidateRules": [
                "required"
            ]
        },
        {
            "fieldName": "ownerName",
            "fieldType": "String"
        },
        {
            "fieldName": "tin",
            "fieldType": "String"
        },
        {
            "fieldName": "user",
            "fieldType": "String",
            "fieldValidateRules": [
                "required"
            ]
        },
        {
            "fieldName": "termsAndConditions",
            "fieldType": "String"
        }
    ],
    "changelogDate": "20160621141124",
    "dto": "no",
    "service": "no",
    "entityTableName": "profile",
    "pagination": "no"
}
